htmlgenim/__init__.py
htmlgenim/generator.py
htmlgenim-0.4.6.dist-info/METADATA
htmlgenim-0.4.6.dist-info/WHEEL
htmlgenim-0.4.6.dist-info/top_level.txt
htmlgenim-0.4.6.dist-info/RECORD
