Metadata-Version: 2.1
Name: htmlgenim
Version: 0.4.6
Summary: HTML-Page Generator
Author: improve
Author-email: vlasav227@mail.ru
Classifier: Programming Language :: Python :: 3
Classifier: License :: OSI Approved :: MIT License
Classifier: Operating System :: OS Independent
Requires-Python: >=3.6
